[
    {
        "match_id": 14058103,
        "kickoff": 1768410000,
        "fixture": "Senegal vs Egypt",
        "league_id": 270,
        "league": "Africa Cup of Nations, Knockout stage",
        "venue": "Stade Ibn-Batouta",
        "tv_channels": [
            {
                "country": "Argentina",
                "channels": [
                    "Claro Sports"
                ]
            },
            {
                "country": "Belize",
                "channels": [
                    "Claro Sports"
                ]
            },
            {
                "country": "Bolivia",
                "channels": [
                    "Claro Sports"
                ]
            },
            {
                "country": "Chile",
                "channels": [
                    "Claro Sports"
                ]
            },
            {
                "country": "Colombia",
                "channels": [
                    "Claro Sports"
                ]
            },
            {
                "country": "Costa Rica",
                "channels": [
                    "Claro Sports"
                ]
            },
            {
                "country": "Cuba",
                "channels": [
                    "Claro Sports"
                ]
            },
            {
                "country": "Dominican Republic",
                "channels": [
                    "Claro Sports"
                ]
            },
            {
                "country": "Ecuador",
                "channels": [
                    "Claro Sports"
                ]
            },
            {
                "country": "El Salvador",
                "channels": [
                    "Claro Sports"
                ]
            },
            {
                "country": "Guatemala",
                "channels": [
                    "Claro Sports"
                ]
            },
            {
                "country": "Honduras",
                "channels": [
                    "Claro Sports"
                ]
            },
            {
                "country": "Mexico",
                "channels": [
                    "Claro Sports"
                ]
            },
            {
                "country": "Nicaragua",
                "channels": [
                    "Claro Sports"
                ]
            },
            {
                "country": "Panama",
                "channels": [
                    "Claro Sports"
                ]
            },
            {
                "country": "Paraguay",
                "channels": [
                    "Claro Sports"
                ]
            },
            {
                "country": "Peru",
                "channels": [
                    "Claro Sports"
                ]
            },
            {
                "country": "Puerto Rico",
                "channels": [
                    "Claro Sports"
                ]
            },
            {
                "country": "United States",
                "channels": [
                    "beIN Sports"
                ]
            },
            {
                "country": "Uruguay",
                "channels": [
                    "Claro Sports"
                ]
            },
            {
                "country": "Venezuela",
                "channels": [
                    "Claro Sports"
                ]
            }
        ]
    },
    {
        "match_id": 14058101,
        "kickoff": 1768420800,
        "fixture": "Nigeria vs Morocco",
        "league_id": 270,
        "league": "Africa Cup of Nations, Knockout stage",
        "venue": "Complexe Sportif Moulay Abdellah",
        "tv_channels": [
            {
                "country": "Argentina",
                "channels": [
                    "Claro Sports"
                ]
            },
            {
                "country": "Belize",
                "channels": [
                    "Claro Sports"
                ]
            },
            {
                "country": "Bolivia",
                "channels": [
                    "Claro Sports"
                ]
            },
            {
                "country": "Chile",
                "channels": [
                    "Claro Sports"
                ]
            },
            {
                "country": "Colombia",
                "channels": [
                    "Claro Sports"
                ]
            },
            {
                "country": "Costa Rica",
                "channels": [
                    "Claro Sports"
                ]
            },
            {
                "country": "Cuba",
                "channels": [
                    "Claro Sports"
                ]
            },
            {
                "country": "Dominican Republic",
                "channels": [
                    "Claro Sports"
                ]
            },
            {
                "country": "Ecuador",
                "channels": [
                    "Claro Sports"
                ]
            },
            {
                "country": "El Salvador",
                "channels": [
                    "Claro Sports"
                ]
            },
            {
                "country": "Guatemala",
                "channels": [
                    "Claro Sports"
                ]
            },
            {
                "country": "Honduras",
                "channels": [
                    "Claro Sports"
                ]
            },
            {
                "country": "Mexico",
                "channels": [
                    "Claro Sports"
                ]
            },
            {
                "country": "Nicaragua",
                "channels": [
                    "Claro Sports"
                ]
            },
            {
                "country": "Panama",
                "channels": [
                    "Claro Sports"
                ]
            },
            {
                "country": "Paraguay",
                "channels": [
                    "Claro Sports"
                ]
            },
            {
                "country": "Peru",
                "channels": [
                    "Claro Sports"
                ]
            },
            {
                "country": "Puerto Rico",
                "channels": [
                    "Claro Sports"
                ]
            },
            {
                "country": "United States",
                "channels": [
                    "beIN Sports"
                ]
            },
            {
                "country": "Uruguay",
                "channels": [
                    "Claro Sports"
                ]
            },
            {
                "country": "Venezuela",
                "channels": [
                    "Claro Sports"
                ]
            }
        ]
    },
    {
        "match_id": 14844295,
        "kickoff": 1768411800,
        "fixture": "Napoli vs Parma",
        "league_id": 23,
        "league": "Serie A",
        "venue": "Stadio Diego Armando Maradona",
        "tv_channels": [
            {
                "country": "Australia",
                "channels": [
                    "Paramount+"
                ]
            },
            {
                "country": "Austria",
                "channels": [
                    "DAZN Austria"
                ]
            },
            {
                "country": "Belize",
                "channels": [
                    "ESPN 2 Norte"
                ]
            },
            {
                "country": "Bolivia",
                "channels": [
                    "Disney+ Premium Chile"
                ]
            },
            {
                "country": "Chile",
                "channels": [
                    "Disney+ Premium Chile"
                ]
            },
            {
                "country": "Costa Rica",
                "channels": [
                    "ESPN 2 Norte"
                ]
            },
            {
                "country": "Denmark",
                "channels": [
                    "TV2 Sport X",
                    "TV2 Play Denmark"
                ]
            },
            {
                "country": "Dominican Republic",
                "channels": [
                    "ESPN 2 Norte"
                ]
            },
            {
                "country": "El Salvador",
                "channels": [
                    "ESPN 2 Norte"
                ]
            },
            {
                "country": "Faroe Islands",
                "channels": [
                    "TV2 Sport X",
                    "TV2 Play Denmark"
                ]
            },
            {
                "country": "Guatemala",
                "channels": [
                    "ESPN 2 Norte"
                ]
            },
            {
                "country": "Honduras",
                "channels": [
                    "ESPN 2 Norte"
                ]
            },
            {
                "country": "Mexico",
                "channels": [
                    "ESPN 2 Norte"
                ]
            },
            {
                "country": "Nicaragua",
                "channels": [
                    "ESPN 2 Norte"
                ]
            },
            {
                "country": "Panama",
                "channels": [
                    "ESPN 2 Norte"
                ]
            },
            {
                "country": "Peru",
                "channels": [
                    "Disney+ Premium Chile"
                ]
            },
            {
                "country": "Russia",
                "channels": [
                    "Match! futbol 1"
                ]
            },
            {
                "country": "United States",
                "channels": [
                    "Fox Deportes",
                    "Paramount+"
                ]
            }
        ]
    },
    {
        "match_id": 14844287,
        "kickoff": 1768419900,
        "fixture": "Inter vs Lecce",
        "league_id": 23,
        "league": "Serie A",
        "venue": "San Siro/Giuseppe Meazza",
        "tv_channels": [
            {
                "country": "Australia",
                "channels": [
                    "Paramount+"
                ]
            },
            {
                "country": "Austria",
                "channels": [
                    "DAZN Austria"
                ]
            },
            {
                "country": "Bolivia",
                "channels": [
                    "Disney+ Premium Chile"
                ]
            },
            {
                "country": "Chile",
                "channels": [
                    "Disney+ Premium Chile"
                ]
            },
            {
                "country": "Denmark",
                "channels": [
                    "TV2 Sport X",
                    "TV2 Play Denmark"
                ]
            },
            {
                "country": "Faroe Islands",
                "channels": [
                    "TV2 Sport X",
                    "TV2 Play Denmark"
                ]
            },
            {
                "country": "Italy",
                "channels": [
                    "DAZN1"
                ]
            },
            {
                "country": "Peru",
                "channels": [
                    "Disney+ Premium Chile"
                ]
            },
            {
                "country": "Russia",
                "channels": [
                    "Match! futbol 1"
                ]
            },
            {
                "country": "San Marino",
                "channels": [
                    "DAZN1"
                ]
            },
            {
                "country": "United States",
                "channels": [
                    "Paramount+"
                ]
            }
        ]
    },
    {
        "match_id": 14844293,
        "kickoff": 1768498200,
        "fixture": "Hellas Verona vs Bologna",
        "league_id": 23,
        "league": "Serie A",
        "venue": "Stadio Marcantonio Bentegodi",
        "tv_channels": []
    },
    {
        "match_id": 14844296,
        "kickoff": 1768506300,
        "fixture": "Como vs Milan",
        "league_id": 23,
        "league": "Serie A",
        "venue": "Stadio Giuseppe Sinigaglia",
        "tv_channels": [
            {
                "country": "Ireland",
                "channels": [
                    "Discovery+",
                    "TNT Sports 3"
                ]
            },
            {
                "country": "United Kingdom",
                "channels": [
                    "Discovery+"
                ]
            }
        ]
    },
    {
        "match_id": 14062164,
        "kickoff": 1768411800,
        "fixture": "VfL Wolfsburg vs FC St. Pauli",
        "league_id": 35,
        "league": "Bundesliga",
        "venue": "Volkswagen Arena",
        "tv_channels": [
            {
                "country": "Austria",
                "channels": [
                    "Sky Go"
                ]
            },
            {
                "country": "Denmark",
                "channels": [
                    "Viaplay",
                    "See"
                ]
            },
            {
                "country": "Finland",
                "channels": [
                    "V Sport 2 Suomi",
                    "VeikkausTV"
                ]
            },
            {
                "country": "Germany",
                "channels": [
                    "Sky Go",
                    "Sky Bundesliga HD 1"
                ]
            },
            {
                "country": "Greenland",
                "channels": [
                    "Viaplay"
                ]
            },
            {
                "country": "Luxembourg",
                "channels": [
                    "Sky Go"
                ]
            },
            {
                "country": "Norway",
                "channels": [
                    "Viaplay"
                ]
            },
            {
                "country": "Sweden",
                "channels": [
                    "Viaplay"
                ]
            },
            {
                "country": "Switzerland",
                "channels": [
                    "Sky Bundesliga HD 1"
                ]
            },
            {
                "country": "United States",
                "channels": [
                    "ESPN App"
                ]
            }
        ]
    },
    {
        "match_id": 14062167,
        "kickoff": 1768419000,
        "fixture": "1. FC Köln vs FC Bayern München",
        "league_id": 35,
        "league": "Bundesliga",
        "venue": "RheinEnergieStadion",
        "tv_channels": [
            {
                "country": "Andorra",
                "channels": [
                    "beIN Sports 3"
                ]
            },
            {
                "country": "Austria",
                "channels": [
                    "Sky Sport Bundesliga",
                    "RTL+",
                    "Sky Go"
                ]
            },
            {
                "country": "Belgium",
                "channels": [
                    "RTL"
                ]
            },
            {
                "country": "Bolivia",
                "channels": [
                    "Disney+ Premium Chile"
                ]
            },
            {
                "country": "Chile",
                "channels": [
                    "Disney+ Premium Chile"
                ]
            },
            {
                "country": "Denmark",
                "channels": [
                    "Viaplay",
                    "See"
                ]
            },
            {
                "country": "Finland",
                "channels": [
                    "V Sport 2 Suomi",
                    "VeikkausTV"
                ]
            },
            {
                "country": "France",
                "channels": [
                    "beIN Sports 3",
                    "RTL"
                ]
            },
            {
                "country": "Germany",
                "channels": [
                    "Sky Go",
                    "RTL+",
                    "Sky Bundesliga HD 1",
                    "Sky Sport Bundesliga UHD",
                    "RTL"
                ]
            },
            {
                "country": "Greenland",
                "channels": [
                    "Viaplay"
                ]
            },
            {
                "country": "Kosovo",
                "channels": [
                    "RTL"
                ]
            },
            {
                "country": "Liechtenstein",
                "channels": [
                    "RTL"
                ]
            },
            {
                "country": "Luxembourg",
                "channels": [
                    "Sky Go",
                    "RTL"
                ]
            },
            {
                "country": "Morocco",
                "channels": [
                    "beIN Sports 3"
                ]
            },
            {
                "country": "Netherlands",
                "channels": [
                    "RTL"
                ]
            },
            {
                "country": "Norway",
                "channels": [
                    "Viaplay"
                ]
            },
            {
                "country": "Peru",
                "channels": [
                    "Disney+ Premium Chile"
                ]
            },
            {
                "country": "Sweden",
                "channels": [
                    "Viaplay"
                ]
            },
            {
                "country": "Switzerland",
                "channels": [
                    "Sky Bundesliga HD 1",
                    "RTL+",
                    "RTL"
                ]
            },
            {
                "country": "United States",
                "channels": [
                    "ESPN App"
                ]
            }
        ]
    },
    {
        "match_id": 14062149,
        "kickoff": 1768419000,
        "fixture": "RB Leipzig vs SC Freiburg",
        "league_id": 35,
        "league": "Bundesliga",
        "venue": "Red Bull Arena",
        "tv_channels": [
            {
                "country": "Andorra",
                "channels": [
                    "beIN Sports MAX 7"
                ]
            },
            {
                "country": "Austria",
                "channels": [
                    "Sky Go"
                ]
            },
            {
                "country": "Bolivia",
                "channels": [
                    "Disney+ Premium Chile"
                ]
            },
            {
                "country": "Chile",
                "channels": [
                    "Disney+ Premium Chile"
                ]
            },
            {
                "country": "Denmark",
                "channels": [
                    "Viaplay"
                ]
            },
            {
                "country": "Finland",
                "channels": [
                    "VeikkausTV"
                ]
            },
            {
                "country": "France",
                "channels": [
                    "beIN Sports MAX 7"
                ]
            },
            {
                "country": "Germany",
                "channels": [
                    "Sky Bundesliga HD 3",
                    "Sky Go"
                ]
            },
            {
                "country": "Greenland",
                "channels": [
                    "Viaplay"
                ]
            },
            {
                "country": "Luxembourg",
                "channels": [
                    "Sky Go"
                ]
            },
            {
                "country": "Norway",
                "channels": [
                    "Viaplay"
                ]
            },
            {
                "country": "Peru",
                "channels": [
                    "Disney+ Premium Chile"
                ]
            },
            {
                "country": "Sweden",
                "channels": [
                    "Viaplay"
                ]
            },
            {
                "country": "Switzerland",
                "channels": [
                    "Sky Bundesliga HD 3"
                ]
            },
            {
                "country": "United States",
                "channels": [
                    "ESPN App"
                ]
            }
        ]
    },
    {
        "match_id": 14062166,
        "kickoff": 1768419000,
        "fixture": "TSG Hoffenheim vs Borussia M'gladbach",
        "league_id": 35,
        "league": "Bundesliga",
        "venue": "PreZero Arena",
        "tv_channels": [
            {
                "country": "Andorra",
                "channels": [
                    "beIN Sports MAX 8"
                ]
            },
            {
                "country": "Argentina",
                "channels": [
                    "ESPN 2 Sur"
                ]
            },
            {
                "country": "Austria",
                "channels": [
                    "Sky Go"
                ]
            },
            {
                "country": "Bolivia",
                "channels": [
                    "Disney+ Premium Chile",
                    "ESPN 2 Sur"
                ]
            },
            {
                "country": "Chile",
                "channels": [
                    "Disney+ Premium Chile",
                    "ESPN 2 Sur"
                ]
            },
            {
                "country": "Colombia",
                "channels": [
                    "ESPN 2 Colombia"
                ]
            },
            {
                "country": "Denmark",
                "channels": [
                    "Viaplay"
                ]
            },
            {
                "country": "Ecuador",
                "channels": [
                    "ESPN 2 Sur"
                ]
            },
            {
                "country": "Finland",
                "channels": [
                    "VeikkausTV"
                ]
            },
            {
                "country": "France",
                "channels": [
                    "beIN Sports MAX 8"
                ]
            },
            {
                "country": "Germany",
                "channels": [
                    "Sky Go",
                    "Sky Bundesliga HD 4"
                ]
            },
            {
                "country": "Greenland",
                "channels": [
                    "Viaplay"
                ]
            },
            {
                "country": "Luxembourg",
                "channels": [
                    "Sky Go"
                ]
            },
            {
                "country": "Norway",
                "channels": [
                    "Viaplay"
                ]
            },
            {
                "country": "Paraguay",
                "channels": [
                    "ESPN 2 Sur"
                ]
            },
            {
                "country": "Peru",
                "channels": [
                    "ESPN 2 Sur",
                    "Disney+ Premium Chile"
                ]
            },
            {
                "country": "Sweden",
                "channels": [
                    "Viaplay"
                ]
            },
            {
                "country": "Switzerland",
                "channels": [
                    "Sky Bundesliga HD 4"
                ]
            },
            {
                "country": "United States",
                "channels": [
                    "ESPN App"
                ]
            },
            {
                "country": "Uruguay",
                "channels": [
                    "ESPN 2 Sur"
                ]
            }
        ]
    },
    {
        "match_id": 14062165,
        "kickoff": 1768505400,
        "fixture": "FC Augsburg vs 1. FC Union Berlin",
        "league_id": 35,
        "league": "Bundesliga",
        "venue": "WWK ARENA",
        "tv_channels": []
    },
    {
        "match_id": 15327736,
        "kickoff": 1768420800,
        "fixture": "Albacete Balompié vs Real Madrid",
        "league_id": 329,
        "league": "Copa del Rey",
        "venue": "TBA",
        "tv_channels": [
            {
                "country": "Andorra",
                "channels": [
                    "TVE La 1"
                ]
            },
            {
                "country": "Finland",
                "channels": [
                    "VeikkausTV"
                ]
            },
            {
                "country": "Spain",
                "channels": [
                    "TVE La 1"
                ]
            }
        ]
    },
    {
        "match_id": 15327738,
        "kickoff": 1768420800,
        "fixture": "Deportivo Alavés vs Rayo Vallecano",
        "league_id": 329,
        "league": "Copa del Rey",
        "venue": "TBA",
        "tv_channels": [
            {
                "country": "Finland",
                "channels": [
                    "VeikkausTV"
                ]
            }
        ]
    },
    {
        "match_id": 15327739,
        "kickoff": 1768420800,
        "fixture": "Real Betis vs Elche",
        "league_id": 329,
        "league": "Copa del Rey",
        "venue": "TBA",
        "tv_channels": [
            {
                "country": "Finland",
                "channels": [
                    "VeikkausTV"
                ]
            }
        ]
    },
    {
        "match_id": 15327742,
        "kickoff": 1768507200,
        "fixture": "Burgos Club de Fútbol vs Valencia",
        "league_id": 329,
        "league": "Copa del Rey",
        "venue": "TBA",
        "tv_channels": []
    },
    {
        "match_id": 15327735,
        "kickoff": 1768507200,
        "fixture": "Real Racing Club vs Barcelona",
        "league_id": 329,
        "league": "Copa del Rey",
        "venue": "TBA",
        "tv_channels": []
    },
    {
        "match_id": 15038064,
        "kickoff": 1768419900,
        "fixture": "Falkirk FC vs Celtic",
        "league_id": 36,
        "league": "Scottish Premiership",
        "venue": "TBA",
        "tv_channels": [
            {
                "country": "Angola",
                "channels": [
                    "ESPN Africa",
                    "DStv Now"
                ]
            },
            {
                "country": "Australia",
                "channels": [
                    "Paramount+"
                ]
            },
            {
                "country": "Benin",
                "channels": [
                    "ESPN Africa"
                ]
            },
            {
                "country": "Botswana",
                "channels": [
                    "DStv Now",
                    "ESPN Africa"
                ]
            },
            {
                "country": "Burkina Faso",
                "channels": [
                    "ESPN Africa",
                    "DStv Now"
                ]
            },
            {
                "country": "Burundi",
                "channels": [
                    "DStv Now",
                    "ESPN Africa"
                ]
            },
            {
                "country": "Cameroon",
                "channels": [
                    "DStv Now",
                    "ESPN Africa"
                ]
            },
            {
                "country": "Cape Verde",
                "channels": [
                    "DStv Now"
                ]
            },
            {
                "country": "Central African Republic",
                "channels": [
                    "ESPN Africa"
                ]
            },
            {
                "country": "Chad",
                "channels": [
                    "DStv Now"
                ]
            },
            {
                "country": "Congo - Brazzaville",
                "channels": [
                    "ESPN Africa",
                    "DStv Now"
                ]
            },
            {
                "country": "Congo - Kinshasa",
                "channels": [
                    "DStv Now"
                ]
            },
            {
                "country": "Côte d’Ivoire",
                "channels": [
                    "DStv Now",
                    "ESPN Africa"
                ]
            },
            {
                "country": "Djibouti",
                "channels": [
                    "DStv Now"
                ]
            },
            {
                "country": "Equatorial Guinea",
                "channels": [
                    "DStv Now",
                    "ESPN Africa"
                ]
            },
            {
                "country": "Eritrea",
                "channels": [
                    "ESPN Africa",
                    "DStv Now"
                ]
            },
            {
                "country": "Eswatini",
                "channels": [
                    "DStv Now",
                    "ESPN Africa"
                ]
            },
            {
                "country": "Ethiopia",
                "channels": [
                    "ESPN Africa",
                    "DStv Now"
                ]
            },
            {
                "country": "Gabon",
                "channels": [
                    "DStv Now",
                    "ESPN Africa"
                ]
            },
            {
                "country": "Gambia",
                "channels": [
                    "DStv Now",
                    "ESPN Africa"
                ]
            },
            {
                "country": "Ghana",
                "channels": [
                    "DStv Now",
                    "ESPN Africa"
                ]
            },
            {
                "country": "Guinea",
                "channels": [
                    "ESPN Africa",
                    "DStv Now"
                ]
            },
            {
                "country": "Guinea-Bissau",
                "channels": [
                    "ESPN Africa",
                    "DStv Now"
                ]
            },
            {
                "country": "Ireland",
                "channels": [
                    "Premier Sports Player",
                    "Premier Sports 1 HD"
                ]
            },
            {
                "country": "Kenya",
                "channels": [
                    "ESPN Africa",
                    "DStv Now"
                ]
            },
            {
                "country": "Lesotho",
                "channels": [
                    "DStv Now",
                    "ESPN Africa"
                ]
            },
            {
                "country": "Liberia",
                "channels": [
                    "ESPN Africa",
                    "DStv Now"
                ]
            },
            {
                "country": "Madagascar",
                "channels": [
                    "ESPN Africa",
                    "DStv Now"
                ]
            },
            {
                "country": "Malawi",
                "channels": [
                    "DStv Now",
                    "ESPN Africa"
                ]
            },
            {
                "country": "Mali",
                "channels": [
                    "DStv Now",
                    "ESPN Africa"
                ]
            },
            {
                "country": "Mauritania",
                "channels": [
                    "DStv Now"
                ]
            },
            {
                "country": "Mauritius",
                "channels": [
                    "DStv Now",
                    "ESPN Africa"
                ]
            },
            {
                "country": "Mayotte",
                "channels": [
                    "ESPN Africa"
                ]
            },
            {
                "country": "Mozambique",
                "channels": [
                    "ESPN Africa",
                    "DStv Now"
                ]
            },
            {
                "country": "Namibia",
                "channels": [
                    "DStv Now",
                    "ESPN Africa"
                ]
            },
            {
                "country": "Niger",
                "channels": [
                    "ESPN Africa",
                    "DStv Now"
                ]
            },
            {
                "country": "Nigeria",
                "channels": [
                    "DStv Now",
                    "ESPN Africa"
                ]
            },
            {
                "country": "Portugal",
                "channels": [
                    "Sport TV5"
                ]
            },
            {
                "country": "Réunion",
                "channels": [
                    "ESPN Africa"
                ]
            },
            {
                "country": "Rwanda",
                "channels": [
                    "ESPN Africa"
                ]
            },
            {
                "country": "São Tomé & Príncipe",
                "channels": [
                    "ESPN Africa"
                ]
            },
            {
                "country": "Senegal",
                "channels": [
                    "ESPN Africa",
                    "DStv Now"
                ]
            },
            {
                "country": "Seychelles",
                "channels": [
                    "DStv Now",
                    "ESPN Africa"
                ]
            },
            {
                "country": "Sierra Leone",
                "channels": [
                    "ESPN Africa",
                    "DStv Now"
                ]
            },
            {
                "country": "South Africa",
                "channels": [
                    "ESPN Africa"
                ]
            },
            {
                "country": "South Sudan",
                "channels": [
                    "DStv Now"
                ]
            },
            {
                "country": "Sudan",
                "channels": [
                    "DStv Now"
                ]
            },
            {
                "country": "Tanzania",
                "channels": [
                    "ESPN Africa",
                    "DStv Now"
                ]
            },
            {
                "country": "Togo",
                "channels": [
                    "DStv Now",
                    "ESPN Africa"
                ]
            },
            {
                "country": "Uganda",
                "channels": [
                    "ESPN Africa",
                    "DStv Now"
                ]
            },
            {
                "country": "United Kingdom",
                "channels": [
                    "Premier Sports 1 HD",
                    "Premier Sports Player"
                ]
            },
            {
                "country": "United States",
                "channels": [
                    "Paramount+"
                ]
            },
            {
                "country": "Zambia",
                "channels": [
                    "ESPN Africa"
                ]
            },
            {
                "country": "Zimbabwe",
                "channels": [
                    "DStv Now",
                    "ESPN Africa"
                ]
            }
        ]
    },
    {
        "match_id": 15038075,
        "kickoff": 1768419900,
        "fixture": "Heart of Midlothian vs St. Mirren",
        "league_id": 36,
        "league": "Scottish Premiership",
        "venue": "TBA",
        "tv_channels": []
    },
    {
        "match_id": 15268210,
        "kickoff": 1768420800,
        "fixture": "Chelsea vs Arsenal",
        "league_id": 21,
        "league": "EFL Cup",
        "venue": "Stamford Bridge",
        "tv_channels": [
            {
                "country": "Andorra",
                "channels": [
                    "beIN SPORTS 2"
                ]
            },
            {
                "country": "Angola",
                "channels": [
                    "SuperSport Maximo",
                    "SuperSport Maximo 2",
                    "SuperSport Premier League",
                    "SuperSport Grandstand",
                    "DStv Now"
                ]
            },
            {
                "country": "Australia",
                "channels": [
                    "Paramount+"
                ]
            },
            {
                "country": "Austria",
                "channels": [
                    "Sky Sports Premier League",
                    "Sky Go"
                ]
            },
            {
                "country": "Benin",
                "channels": [
                    "SuperSport Premier League",
                    "SuperSport Maximo",
                    "SuperSport Maximo 2",
                    "SuperSport Grandstand"
                ]
            },
            {
                "country": "Botswana",
                "channels": [
                    "DStv Now",
                    "SuperSport Premier League",
                    "SuperSport Grandstand",
                    "SuperSport Maximo",
                    "SuperSport Maximo 2"
                ]
            },
            {
                "country": "Burkina Faso",
                "channels": [
                    "SuperSport Maximo 2",
                    "SuperSport Maximo",
                    "DStv Now",
                    "SuperSport Premier League",
                    "SuperSport Grandstand"
                ]
            },
            {
                "country": "Burundi",
                "channels": [
                    "SuperSport Grandstand",
                    "Startimes World Football",
                    "DStv Now",
                    "SuperSport Premier League",
                    "SuperSport Maximo",
                    "SuperSport Maximo 2"
                ]
            },
            {
                "country": "Cameroon",
                "channels": [
                    "StarTimes App",
                    "SuperSport Maximo",
                    "SuperSport Maximo 2",
                    "SuperSport Premier League",
                    "DStv Now",
                    "SuperSport Grandstand"
                ]
            },
            {
                "country": "Cape Verde",
                "channels": [
                    "SuperSport Premier League",
                    "DStv Now",
                    "SuperSport Maximo 2",
                    "SuperSport Grandstand",
                    "SuperSport Maximo"
                ]
            },
            {
                "country": "Central African Republic",
                "channels": [
                    "SuperSport Premier League",
                    "SuperSport Maximo 2",
                    "SuperSport Grandstand",
                    "SuperSport Maximo"
                ]
            },
            {
                "country": "Chad",
                "channels": [
                    "SuperSport Grandstand",
                    "SuperSport Maximo 2",
                    "SuperSport Premier League",
                    "SuperSport Maximo",
                    "DStv Now"
                ]
            },
            {
                "country": "Comoros",
                "channels": [
                    "SuperSport Maximo",
                    "SuperSport Grandstand",
                    "SuperSport Premier League",
                    "SuperSport Maximo 2"
                ]
            },
            {
                "country": "Congo - Brazzaville",
                "channels": [
                    "Startimes World Football",
                    "SuperSport Maximo 2",
                    "SuperSport Premier League",
                    "SuperSport Grandstand",
                    "DStv Now",
                    "SuperSport Maximo",
                    "StarTimes App"
                ]
            },
            {
                "country": "Congo - Kinshasa",
                "channels": [
                    "StarTimes App",
                    "DStv Now",
                    "SuperSport Premier League",
                    "SuperSport Maximo 2",
                    "SuperSport Maximo",
                    "SuperSport Grandstand"
                ]
            },
            {
                "country": "Côte d’Ivoire",
                "channels": [
                    "SuperSport Premier League",
                    "DStv Now",
                    "SuperSport Maximo",
                    "SuperSport Grandstand",
                    "SuperSport Maximo 2"
                ]
            },
            {
                "country": "Denmark",
                "channels": [
                    "Viaplay"
                ]
            },
            {
                "country": "Djibouti",
                "channels": [
                    "DStv Now",
                    "SuperSport Grandstand",
                    "SuperSport Maximo",
                    "SuperSport Premier League",
                    "SuperSport Maximo 2"
                ]
            },
            {
                "country": "Equatorial Guinea",
                "channels": [
                    "SuperSport Grandstand",
                    "SuperSport Maximo",
                    "SuperSport Premier League",
                    "DStv Now",
                    "SuperSport Maximo 2"
                ]
            },
            {
                "country": "Eritrea",
                "channels": [
                    "DStv Now",
                    "SuperSport Maximo 2",
                    "SuperSport Maximo",
                    "SuperSport Grandstand",
                    "SuperSport Premier League"
                ]
            },
            {
                "country": "Eswatini",
                "channels": [
                    "SuperSport Maximo",
                    "DStv Now",
                    "SuperSport Premier League",
                    "SuperSport Maximo 2",
                    "SuperSport Grandstand"
                ]
            },
            {
                "country": "Ethiopia",
                "channels": [
                    "SuperSport Premier League",
                    "SuperSport Grandstand",
                    "SuperSport Maximo 2",
                    "SuperSport Maximo",
                    "DStv Now"
                ]
            },
            {
                "country": "France",
                "channels": [
                    "beIN SPORTS 2"
                ]
            },
            {
                "country": "Gabon",
                "channels": [
                    "SuperSport Premier League",
                    "SuperSport Maximo",
                    "SuperSport Grandstand",
                    "SuperSport Maximo 2",
                    "DStv Now"
                ]
            },
            {
                "country": "Gambia",
                "channels": [
                    "SuperSport Grandstand",
                    "SuperSport Premier League",
                    "SuperSport Maximo 2",
                    "DStv Now",
                    "SuperSport Maximo"
                ]
            },
            {
                "country": "Germany",
                "channels": [
                    "Sky Go"
                ]
            },
            {
                "country": "Ghana",
                "channels": [
                    "SuperSport Premier League",
                    "DStv Now",
                    "StarTimes App",
                    "SuperSport Maximo",
                    "SuperSport Maximo 2",
                    "Startimes World Football",
                    "SuperSport Grandstand"
                ]
            },
            {
                "country": "Greenland",
                "channels": [
                    "Viaplay"
                ]
            },
            {
                "country": "Guinea",
                "channels": [
                    "Startimes World Football",
                    "SuperSport Maximo",
                    "StarTimes App",
                    "SuperSport Maximo 2",
                    "SuperSport Grandstand",
                    "SuperSport Premier League",
                    "DStv Now"
                ]
            },
            {
                "country": "Guinea-Bissau",
                "channels": [
                    "DStv Now",
                    "SuperSport Maximo 2",
                    "SuperSport Grandstand",
                    "SuperSport Premier League",
                    "SuperSport Maximo"
                ]
            },
            {
                "country": "Ireland",
                "channels": [
                    "Sky Sports Football",
                    "Sky Sports Main Event",
                    "Sky Sports Ultra HDR",
                    "Sky Sports Ultra HD"
                ]
            },
            {
                "country": "Kenya",
                "channels": [
                    "Azam Sports 4 HD",
                    "DStv Now",
                    "StarTimes App",
                    "SuperSport Maximo",
                    "SuperSport Grandstand",
                    "SuperSport Maximo 2",
                    "SuperSport Premier League",
                    "Startimes World Football"
                ]
            },
            {
                "country": "Lesotho",
                "channels": [
                    "SuperSport Maximo 2",
                    "SuperSport Premier League",
                    "StarTimes App",
                    "SuperSport Maximo",
                    "DStv Now",
                    "Startimes World Football",
                    "SuperSport Grandstand"
                ]
            },
            {
                "country": "Liberia",
                "channels": [
                    "SuperSport Premier League",
                    "SuperSport Maximo 2",
                    "SuperSport Grandstand",
                    "DStv Now",
                    "SuperSport Maximo"
                ]
            },
            {
                "country": "Luxembourg",
                "channels": [
                    "Sky Go"
                ]
            },
            {
                "country": "Madagascar",
                "channels": [
                    "SuperSport Grandstand",
                    "SuperSport Maximo",
                    "SuperSport Maximo 2",
                    "DStv Now",
                    "SuperSport Premier League",
                    "StarTimes App"
                ]
            },
            {
                "country": "Malawi",
                "channels": [
                    "SuperSport Maximo 2",
                    "SuperSport Maximo",
                    "Azam Sports 4 HD",
                    "StarTimes App",
                    "SuperSport Premier League",
                    "DStv Now",
                    "SuperSport Grandstand"
                ]
            },
            {
                "country": "Mali",
                "channels": [
                    "SuperSport Premier League",
                    "DStv Now",
                    "SuperSport Maximo",
                    "SuperSport Grandstand",
                    "SuperSport Maximo 2"
                ]
            },
            {
                "country": "Mauritania",
                "channels": [
                    "SuperSport Grandstand",
                    "SuperSport Maximo",
                    "SuperSport Premier League",
                    "DStv Now",
                    "SuperSport Maximo 2"
                ]
            },
            {
                "country": "Mauritius",
                "channels": [
                    "DStv Now",
                    "SuperSport Grandstand",
                    "SuperSport Maximo 2",
                    "SuperSport Premier League",
                    "SuperSport Maximo"
                ]
            },
            {
                "country": "Mayotte",
                "channels": [
                    "SuperSport Grandstand",
                    "SuperSport Maximo",
                    "SuperSport Maximo 2",
                    "SuperSport Premier League"
                ]
            },
            {
                "country": "Monaco",
                "channels": [
                    "beIN SPORTS 2"
                ]
            },
            {
                "country": "Mozambique",
                "channels": [
                    "SuperSport Maximo",
                    "DStv Now",
                    "SuperSport Grandstand",
                    "StarTimes App",
                    "SuperSport Maximo 2",
                    "SuperSport Premier League",
                    "Startimes World Football"
                ]
            },
            {
                "country": "Namibia",
                "channels": [
                    "SuperSport Maximo",
                    "SuperSport Grandstand",
                    "DStv Now",
                    "SuperSport Maximo 2",
                    "SuperSport Premier League"
                ]
            },
            {
                "country": "Niger",
                "channels": [
                    "DStv Now",
                    "SuperSport Maximo 2",
                    "SuperSport Premier League",
                    "SuperSport Grandstand",
                    "SuperSport Maximo"
                ]
            },
            {
                "country": "Nigeria",
                "channels": [
                    "StarTimes App",
                    "Startimes World Football",
                    "DStv Now",
                    "SuperSport Maximo",
                    "SuperSport Maximo 2"
                ]
            },
            {
                "country": "Norway",
                "channels": [
                    "Viaplay"
                ]
            },
            {
                "country": "Portugal",
                "channels": [
                    "Sport TV3"
                ]
            },
            {
                "country": "Réunion",
                "channels": [
                    "SuperSport Maximo",
                    "SuperSport Premier League",
                    "SuperSport Maximo 2",
                    "SuperSport Grandstand"
                ]
            },
            {
                "country": "Rwanda",
                "channels": [
                    "StarTimes App",
                    "SuperSport Premier League",
                    "SuperSport Maximo 2",
                    "Startimes World Football",
                    "SuperSport Grandstand",
                    "SuperSport Maximo",
                    "Azam Sports 4 HD"
                ]
            },
            {
                "country": "São Tomé & Príncipe",
                "channels": [
                    "SuperSport Grandstand",
                    "SuperSport Maximo",
                    "SuperSport Maximo 2",
                    "SuperSport Premier League"
                ]
            },
            {
                "country": "Senegal",
                "channels": [
                    "SuperSport Maximo 2",
                    "SuperSport Grandstand",
                    "DStv Now",
                    "SuperSport Premier League",
                    "SuperSport Maximo"
                ]
            },
            {
                "country": "Seychelles",
                "channels": [
                    "DStv Now",
                    "SuperSport Maximo",
                    "SuperSport Grandstand",
                    "SuperSport Premier League",
                    "SuperSport Maximo 2"
                ]
            },
            {
                "country": "Sierra Leone",
                "channels": [
                    "SuperSport Maximo",
                    "Startimes World Football",
                    "SuperSport Grandstand",
                    "SuperSport Premier League",
                    "DStv Now",
                    "StarTimes App",
                    "SuperSport Maximo 2"
                ]
            },
            {
                "country": "Somalia",
                "channels": [
                    "SuperSport Maximo 2",
                    "SuperSport Premier League",
                    "SuperSport Maximo",
                    "SuperSport Grandstand"
                ]
            },
            {
                "country": "South Africa",
                "channels": [
                    "SuperSport Maximo 2",
                    "Startimes World Football",
                    "StarTimes App",
                    "SuperSport Maximo"
                ]
            },
            {
                "country": "South Sudan",
                "channels": [
                    "SuperSport Grandstand",
                    "SuperSport Maximo",
                    "DStv Now",
                    "SuperSport Maximo 2",
                    "SuperSport Premier League"
                ]
            },
            {
                "country": "Sudan",
                "channels": [
                    "SuperSport Maximo",
                    "DStv Now",
                    "SuperSport Maximo 2",
                    "SuperSport Grandstand",
                    "SuperSport Premier League"
                ]
            },
            {
                "country": "Sweden",
                "channels": [
                    "Viaplay"
                ]
            },
            {
                "country": "Tanzania",
                "channels": [
                    "SuperSport Premier League",
                    "SuperSport Grandstand",
                    "Startimes World Football",
                    "DStv Now",
                    "Azam Sports 4 HD",
                    "SuperSport Maximo",
                    "StarTimes App",
                    "SuperSport Maximo 2"
                ]
            },
            {
                "country": "Togo",
                "channels": [
                    "DStv Now",
                    "SuperSport Grandstand",
                    "SuperSport Maximo 2",
                    "SuperSport Premier League",
                    "SuperSport Maximo"
                ]
            },
            {
                "country": "Uganda",
                "channels": [
                    "Startimes World Football",
                    "SuperSport Maximo 2",
                    "Azam Sports 4 HD",
                    "SuperSport Grandstand",
                    "StarTimes App",
                    "SuperSport Premier League",
                    "DStv Now",
                    "SuperSport Maximo"
                ]
            },
            {
                "country": "United Kingdom",
                "channels": [
                    "Sky Sports Football",
                    "Sky Sports Ultra HD",
                    "Sky Sports Main Event"
                ]
            },
            {
                "country": "United States",
                "channels": [
                    "Paramount+"
                ]
            },
            {
                "country": "Zambia",
                "channels": [
                    "Azam Sports 4 HD",
                    "SuperSport Maximo",
                    "SuperSport Maximo 2",
                    "StarTimes App",
                    "SuperSport Premier League",
                    "SuperSport Grandstand"
                ]
            },
            {
                "country": "Zimbabwe",
                "channels": [
                    "DStv Now",
                    "SuperSport Grandstand",
                    "Azam Sports 4 HD",
                    "SuperSport Premier League",
                    "SuperSport Maximo 2",
                    "SuperSport Maximo"
                ]
            }
        ]
    },
    {
        "match_id": 15267915,
        "kickoff": 1768402800,
        "fixture": "Sporting CP vs AVS - Futebol SAD",
        "league_id": 336,
        "league": "Taça de Portugal",
        "venue": "TBA",
        "tv_channels": []
    },
    {
        "match_id": 15286007,
        "kickoff": 1768416300,
        "fixture": "AD Fafe vs Sporting Braga",
        "league_id": 336,
        "league": "Taça de Portugal",
        "venue": "TBA",
        "tv_channels": [
            {
                "country": "Algeria",
                "channels": [
                    "beIN Sports Xtra"
                ]
            },
            {
                "country": "Bahrain",
                "channels": [
                    "beIN Sports Xtra"
                ]
            },
            {
                "country": "Canada",
                "channels": [
                    "beIN Sports Xtra"
                ]
            },
            {
                "country": "Chad",
                "channels": [
                    "beIN Sports Xtra"
                ]
            },
            {
                "country": "Djibouti",
                "channels": [
                    "beIN Sports Xtra"
                ]
            },
            {
                "country": "Egypt",
                "channels": [
                    "beIN Sports Xtra"
                ]
            },
            {
                "country": "Iraq",
                "channels": [
                    "beIN Sports Xtra"
                ]
            },
            {
                "country": "Jordan",
                "channels": [
                    "beIN Sports Xtra"
                ]
            },
            {
                "country": "Kuwait",
                "channels": [
                    "beIN Sports Xtra"
                ]
            },
            {
                "country": "Lebanon",
                "channels": [
                    "beIN Sports Xtra"
                ]
            },
            {
                "country": "Libya",
                "channels": [
                    "beIN Sports Xtra"
                ]
            },
            {
                "country": "Mauritania",
                "channels": [
                    "beIN Sports Xtra"
                ]
            },
            {
                "country": "Morocco",
                "channels": [
                    "beIN Sports Xtra"
                ]
            },
            {
                "country": "Oman",
                "channels": [
                    "beIN Sports Xtra"
                ]
            },
            {
                "country": "Palestine",
                "channels": [
                    "beIN Sports Xtra"
                ]
            },
            {
                "country": "Portugal",
                "channels": [
                    "Sport TV2"
                ]
            },
            {
                "country": "Qatar",
                "channels": [
                    "beIN Sports Xtra"
                ]
            },
            {
                "country": "Somalia",
                "channels": [
                    "beIN Sports Xtra"
                ]
            },
            {
                "country": "South Sudan",
                "channels": [
                    "beIN Sports Xtra"
                ]
            },
            {
                "country": "Sudan",
                "channels": [
                    "beIN Sports Xtra"
                ]
            },
            {
                "country": "Syria",
                "channels": [
                    "beIN Sports Xtra"
                ]
            },
            {
                "country": "Tunisia",
                "channels": [
                    "beIN Sports Xtra"
                ]
            },
            {
                "country": "United Arab Emirates",
                "channels": [
                    "beIN Sports Xtra"
                ]
            },
            {
                "country": "United States",
                "channels": [
                    "beIN Sports Xtra"
                ]
            },
            {
                "country": "Yemen",
                "channels": [
                    "beIN Sports Xtra"
                ]
            }
        ]
    },
    {
        "match_id": 15267916,
        "kickoff": 1768423500,
        "fixture": "FC Porto vs Benfica",
        "league_id": 336,
        "league": "Taça de Portugal",
        "venue": "TBA",
        "tv_channels": [
            {
                "country": "Algeria",
                "channels": [
                    "beIN Sports Xtra"
                ]
            },
            {
                "country": "Bahrain",
                "channels": [
                    "beIN Sports Xtra"
                ]
            },
            {
                "country": "Brazil",
                "channels": [
                    "RTP Internacional"
                ]
            },
            {
                "country": "Canada",
                "channels": [
                    "beIN Sports Xtra"
                ]
            },
            {
                "country": "Chad",
                "channels": [
                    "beIN Sports Xtra"
                ]
            },
            {
                "country": "Djibouti",
                "channels": [
                    "beIN Sports Xtra"
                ]
            },
            {
                "country": "Egypt",
                "channels": [
                    "beIN Sports Xtra"
                ]
            },
            {
                "country": "Iraq",
                "channels": [
                    "beIN Sports Xtra"
                ]
            },
            {
                "country": "Jordan",
                "channels": [
                    "beIN Sports Xtra"
                ]
            },
            {
                "country": "Kuwait",
                "channels": [
                    "beIN Sports Xtra"
                ]
            },
            {
                "country": "Lebanon",
                "channels": [
                    "beIN Sports Xtra"
                ]
            },
            {
                "country": "Lesotho",
                "channels": [
                    "RTP Internacional"
                ]
            },
            {
                "country": "Libya",
                "channels": [
                    "beIN Sports Xtra"
                ]
            },
            {
                "country": "Mauritania",
                "channels": [
                    "beIN Sports Xtra"
                ]
            },
            {
                "country": "Morocco",
                "channels": [
                    "beIN Sports Xtra"
                ]
            },
            {
                "country": "Nigeria",
                "channels": [
                    "RTP Internacional"
                ]
            },
            {
                "country": "Oman",
                "channels": [
                    "beIN Sports Xtra"
                ]
            },
            {
                "country": "Palestine",
                "channels": [
                    "beIN Sports Xtra"
                ]
            },
            {
                "country": "Portugal",
                "channels": [
                    "Sport TV1",
                    "RTP 1",
                    "RTP Internacional"
                ]
            },
            {
                "country": "Qatar",
                "channels": [
                    "beIN Sports Xtra"
                ]
            },
            {
                "country": "Somalia",
                "channels": [
                    "beIN Sports Xtra"
                ]
            },
            {
                "country": "South Africa",
                "channels": [
                    "RTP Internacional"
                ]
            },
            {
                "country": "South Sudan",
                "channels": [
                    "beIN Sports Xtra"
                ]
            },
            {
                "country": "Sudan",
                "channels": [
                    "beIN Sports Xtra"
                ]
            },
            {
                "country": "Switzerland",
                "channels": [
                    "RTP Internacional"
                ]
            },
            {
                "country": "Syria",
                "channels": [
                    "beIN Sports Xtra"
                ]
            },
            {
                "country": "Tunisia",
                "channels": [
                    "beIN Sports Xtra"
                ]
            },
            {
                "country": "United Arab Emirates",
                "channels": [
                    "beIN Sports Xtra"
                ]
            },
            {
                "country": "United States",
                "channels": [
                    "beIN Sports Xtra"
                ]
            },
            {
                "country": "Venezuela",
                "channels": [
                    "RTP Internacional"
                ]
            },
            {
                "country": "Yemen",
                "channels": [
                    "beIN Sports Xtra"
                ]
            }
        ]
    },
    {
        "match_id": 15190951,
        "kickoff": 1768402800,
        "fixture": "İstanbulspor vs Trabzonspor",
        "league_id": 96,
        "league": "Turkiye Kupasi, Group A",
        "venue": "TBA",
        "tv_channels": []
    },
    {
        "match_id": 15187113,
        "kickoff": 1768384800,
        "fixture": "Aliağa FK vs Samsunspor",
        "league_id": 96,
        "league": "Turkiye Kupasi, Group B",
        "venue": "TBA",
        "tv_channels": [
            {
                "country": "Albania",
                "channels": [
                    "A Spor"
                ]
            },
            {
                "country": "Kosovo",
                "channels": [
                    "A Spor"
                ]
            },
            {
                "country": "Türkiye",
                "channels": [
                    "A Spor"
                ]
            }
        ]
    },
    {
        "match_id": 15187119,
        "kickoff": 1768393800,
        "fixture": "Antalyaspor vs Gençlerbirliği",
        "league_id": 96,
        "league": "Turkiye Kupasi, Group B",
        "venue": "TBA",
        "tv_channels": []
    },
    {
        "match_id": 15187125,
        "kickoff": 1768480200,
        "fixture": "Eyüpspor vs Iğdır FK",
        "league_id": 96,
        "league": "Turkiye Kupasi, Group B",
        "venue": "TBA",
        "tv_channels": []
    },
    {
        "match_id": 15187115,
        "kickoff": 1768489200,
        "fixture": "Bodrum FK vs Konyaspor",
        "league_id": 96,
        "league": "Turkiye Kupasi, Group B",
        "venue": "TBA",
        "tv_channels": []
    },
    {
        "match_id": 15187127,
        "kickoff": 1768411800,
        "fixture": "Beyoğlu Yeni Çarşı FAŞ vs Fenerbahçe",
        "league_id": 96,
        "league": "Turkiye Kupasi, Group C",
        "venue": "TBA",
        "tv_channels": [
            {
                "country": "Albania",
                "channels": [
                    "A Spor"
                ]
            },
            {
                "country": "Kosovo",
                "channels": [
                    "A Spor"
                ]
            },
            {
                "country": "Türkiye",
                "channels": [
                    "A Spor"
                ]
            }
        ]
    },
    {
        "match_id": 15187141,
        "kickoff": 1768471200,
        "fixture": "Erzurumspor FK vs Çaykur Rizespor",
        "league_id": 96,
        "league": "Turkiye Kupasi, Group C",
        "venue": "TBA",
        "tv_channels": []
    },
    {
        "match_id": 15187142,
        "kickoff": 1768498200,
        "fixture": "Beşiktaş JK vs Keçiörengücü",
        "league_id": 96,
        "league": "Turkiye Kupasi, Group C",
        "venue": "TBA",
        "tv_channels": []
    },
    {
        "match_id": 15253788,
        "kickoff": 1768412700,
        "fixture": "FC Den Bosch vs PSV Eindhoven",
        "league_id": 330,
        "league": "KNVB beker",
        "venue": "TBA",
        "tv_channels": []
    },
    {
        "match_id": 15253791,
        "kickoff": 1768417200,
        "fixture": "Almere City FC vs SC Telstar",
        "league_id": 330,
        "league": "KNVB beker",
        "venue": "TBA",
        "tv_channels": []
    },
    {
        "match_id": 15253793,
        "kickoff": 1768417200,
        "fixture": "Go Ahead Eagles vs Heracles Almelo",
        "league_id": 330,
        "league": "KNVB beker",
        "venue": "TBA",
        "tv_channels": []
    },
    {
        "match_id": 15253790,
        "kickoff": 1768420800,
        "fixture": "AZ Alkmaar vs AFC Ajax",
        "league_id": 330,
        "league": "KNVB beker",
        "venue": "TBA",
        "tv_channels": []
    },
    {
        "match_id": 15253787,
        "kickoff": 1768499100,
        "fixture": "SC Heerenveen vs RKC Waalwijk",
        "league_id": 330,
        "league": "KNVB beker",
        "venue": "TBA",
        "tv_channels": []
    },
    {
        "match_id": 15268268,
        "kickoff": 1768507200,
        "fixture": "Sparta Rotterdam vs FC Volendam",
        "league_id": 330,
        "league": "KNVB beker",
        "venue": "TBA",
        "tv_channels": []
    },
    {
        "match_id": 15238905,
        "kickoff": 1768438800,
        "fixture": "Club América vs Atlético San Luis",
        "league_id": 11620,
        "league": "Liga MX, Clausura",
        "venue": "Estadio Azteca",
        "tv_channels": [
            {
                "country": "Costa Rica",
                "channels": [
                    "TUDN"
                ]
            },
            {
                "country": "Dominican Republic",
                "channels": [
                    "TUDN"
                ]
            },
            {
                "country": "El Salvador",
                "channels": [
                    "TUDN"
                ]
            },
            {
                "country": "Guatemala",
                "channels": [
                    "TUDN"
                ]
            },
            {
                "country": "Honduras",
                "channels": [
                    "TUDN"
                ]
            },
            {
                "country": "Mexico",
                "channels": [
                    "TUDN"
                ]
            },
            {
                "country": "Nicaragua",
                "channels": [
                    "TUDN"
                ]
            },
            {
                "country": "Panama",
                "channels": [
                    "TUDN"
                ]
            },
            {
                "country": "United States",
                "channels": [
                    "UniMás",
                    "TUDN"
                ]
            }
        ]
    },
    {
        "match_id": 15238906,
        "kickoff": 1768438800,
        "fixture": "Querétaro FC vs Club Tijuana",
        "league_id": 11620,
        "league": "Liga MX, Clausura",
        "venue": "Estadio La Corregidora",
        "tv_channels": []
    },
    {
        "match_id": 15238908,
        "kickoff": 1768446000,
        "fixture": "CD Toluca vs Santos Laguna",
        "league_id": 11620,
        "league": "Liga MX, Clausura",
        "venue": "Estadio Nemesio Diez",
        "tv_channels": [
            {
                "country": "Costa Rica",
                "channels": [
                    "TUDN"
                ]
            },
            {
                "country": "Dominican Republic",
                "channels": [
                    "TUDN"
                ]
            },
            {
                "country": "El Salvador",
                "channels": [
                    "TUDN"
                ]
            },
            {
                "country": "Guatemala",
                "channels": [
                    "TUDN"
                ]
            },
            {
                "country": "Honduras",
                "channels": [
                    "TUDN"
                ]
            },
            {
                "country": "Mexico",
                "channels": [
                    "TUDN"
                ]
            },
            {
                "country": "Nicaragua",
                "channels": [
                    "TUDN"
                ]
            },
            {
                "country": "Panama",
                "channels": [
                    "TUDN"
                ]
            },
            {
                "country": "United States",
                "channels": [
                    "TUDN"
                ]
            }
        ]
    },
    {
        "match_id": 15238907,
        "kickoff": 1768446360,
        "fixture": "Tigres UANL vs Pumas UNAM",
        "league_id": 11620,
        "league": "Liga MX, Clausura",
        "venue": "Estadio Universitario (UANL)",
        "tv_channels": []
    },
    {
        "match_id": 15176505,
        "kickoff": 1768428000,
        "fixture": "EC Primavera vs Mirassol",
        "league_id": 372,
        "league": "Paulista Série A1",
        "venue": "Estádio Ítalo Mário Limongi",
        "tv_channels": []
    },
    {
        "match_id": 15176510,
        "kickoff": 1768429800,
        "fixture": "Palmeiras vs Santos",
        "league_id": 372,
        "league": "Paulista Série A1",
        "venue": "Allianz Parque",
        "tv_channels": [
            {
                "country": "Brazil",
                "channels": [
                    "TNT",
                    "Record"
                ]
            }
        ]
    },
    {
        "match_id": 15176509,
        "kickoff": 1768435200,
        "fixture": "Ponte Preta vs AE Velo Clube",
        "league_id": 372,
        "league": "Paulista Série A1",
        "venue": "Moisés Lucarelli",
        "tv_channels": []
    },
    {
        "match_id": 15176520,
        "kickoff": 1768514400,
        "fixture": "Botafogo-SP vs EC Noroeste",
        "league_id": 372,
        "league": "Paulista Série A1",
        "venue": "Estádio Santa Cruz",
        "tv_channels": []
    },
    {
        "match_id": 15176519,
        "kickoff": 1768516200,
        "fixture": "Red Bull Bragantino vs Corinthians",
        "league_id": 372,
        "league": "Paulista Série A1",
        "venue": "Estádio Nabi Abi Chedid",
        "tv_channels": []
    },
    {
        "match_id": 15176507,
        "kickoff": 1768524300,
        "fixture": "São Paulo vs São Bernardo",
        "league_id": 372,
        "league": "Paulista Série A1",
        "venue": "Morumbi",
        "tv_channels": []
    },
    {
        "match_id": 14671714,
        "kickoff": 1768552500,
        "fixture": "Melbourne City vs Auckland FC",
        "league_id": 136,
        "league": "A-League Men",
        "venue": "Melbourne Rectangular Stadium",
        "tv_channels": []
    },
    {
        "match_id": 14671706,
        "kickoff": 1768560300,
        "fixture": "Perth Glory vs Brisbane Roar",
        "league_id": 136,
        "league": "A-League Men",
        "venue": "HBF Park",
        "tv_channels": []
    },
    {
        "match_id": 14771943,
        "kickoff": 1768401900,
        "fixture": "Al-Qadsiah vs Al-Fayha",
        "league_id": 955,
        "league": "Saudi Pro League",
        "venue": "Prince Saud bin Jalawi Stadium",
        "tv_channels": []
    },
    {
        "match_id": 14771933,
        "kickoff": 1768411800,
        "fixture": "Al-Ahli vs Al-Taawoun",
        "league_id": 955,
        "league": "Saudi Pro League",
        "venue": "Alinma Stadium",
        "tv_channels": [
            {
                "country": "Burundi",
                "channels": [
                    "Startimes World Football"
                ]
            },
            {
                "country": "Cameroon",
                "channels": [
                    "StarTimes App"
                ]
            },
            {
                "country": "Congo - Brazzaville",
                "channels": [
                    "Startimes World Football",
                    "StarTimes App"
                ]
            },
            {
                "country": "Congo - Kinshasa",
                "channels": [
                    "StarTimes App"
                ]
            },
            {
                "country": "Ghana",
                "channels": [
                    "Startimes World Football",
                    "StarTimes App"
                ]
            },
            {
                "country": "Guinea",
                "channels": [
                    "Startimes World Football",
                    "StarTimes App"
                ]
            },
            {
                "country": "Kenya",
                "channels": [
                    "StarTimes App",
                    "Startimes World Football"
                ]
            },
            {
                "country": "Lesotho",
                "channels": [
                    "StarTimes App",
                    "Startimes World Football"
                ]
            },
            {
                "country": "Madagascar",
                "channels": [
                    "StarTimes App"
                ]
            },
            {
                "country": "Malawi",
                "channels": [
                    "StarTimes App"
                ]
            },
            {
                "country": "Mozambique",
                "channels": [
                    "StarTimes App",
                    "Startimes World Football"
                ]
            },
            {
                "country": "Nigeria",
                "channels": [
                    "StarTimes App",
                    "Startimes World Football"
                ]
            },
            {
                "country": "Portugal",
                "channels": [
                    "Sport TV4"
                ]
            },
            {
                "country": "Rwanda",
                "channels": [
                    "Startimes World Football",
                    "StarTimes App"
                ]
            },
            {
                "country": "Sierra Leone",
                "channels": [
                    "Startimes World Football",
                    "StarTimes App"
                ]
            },
            {
                "country": "South Africa",
                "channels": [
                    "StarTimes App",
                    "Startimes World Football"
                ]
            },
            {
                "country": "Tanzania",
                "channels": [
                    "StarTimes App",
                    "Startimes World Football"
                ]
            },
            {
                "country": "Uganda",
                "channels": [
                    "StarTimes App",
                    "Startimes World Football"
                ]
            },
            {
                "country": "United States",
                "channels": [
                    "Fox Sports 2"
                ]
            },
            {
                "country": "Zambia",
                "channels": [
                    "StarTimes App"
                ]
            }
        ]
    },
    {
        "match_id": 14771938,
        "kickoff": 1768411800,
        "fixture": "Al-Shabab vs Neom SC",
        "league_id": 955,
        "league": "Saudi Pro League",
        "venue": "Al-Awwal Park",
        "tv_channels": []
    },
    {
        "match_id": 15306996,
        "kickoff": 1768419000,
        "fixture": "FC Sion vs FC Winterthur",
        "league_id": 215,
        "league": "Swiss Super League",
        "venue": "Tourbillon",
        "tv_channels": []
    },
    {
        "match_id": 14038823,
        "kickoff": 1768419000,
        "fixture": "Servette FC vs FC Lausanne-Sport",
        "league_id": 215,
        "league": "Swiss Super League",
        "venue": "Stade de Genève",
        "tv_channels": []
    },
    {
        "match_id": 14671875,
        "kickoff": 1768542600,
        "fixture": "Melbourne City vs Newcastle Jets",
        "league_id": 1894,
        "league": "A-League, Women",
        "venue": "TBA",
        "tv_channels": []
    },
    {
        "match_id": 14671874,
        "kickoff": 1768550400,
        "fixture": "Western Sydney Wanderers vs Brisbane Roar",
        "league_id": 1894,
        "league": "A-League, Women",
        "venue": "TBA",
        "tv_channels": []
    },
    {
        "match_id": 15192300,
        "kickoff": 1768417200,
        "fixture": "Northampton Town vs Walsall",
        "league_id": 334,
        "league": "EFL Trophy, Knockout stage",
        "venue": "TBA",
        "tv_channels": [
            {
                "country": "Ireland",
                "channels": [
                    "Sky Sports+"
                ]
            },
            {
                "country": "United Kingdom",
                "channels": [
                    "Sky Sports+"
                ]
            }
        ]
    },
    {
        "match_id": 15211534,
        "kickoff": 1768487400,
        "fixture": "Al-Wakrah vs Al Duhail",
        "league_id": 825,
        "league": "Stars League",
        "venue": "TBA",
        "tv_channels": []
    },
    {
        "match_id": 15211545,
        "kickoff": 1768494600,
        "fixture": "Al-Arabi SC vs Al-Gharafa",
        "league_id": 825,
        "league": "Stars League",
        "venue": "TBA",
        "tv_channels": []
    },
    {
        "match_id": 15010554,
        "kickoff": 1768405500,
        "fixture": "Al-Sharjah vs Al Bataeh",
        "league_id": 971,
        "league": "Pro League",
        "venue": "TBA",
        "tv_channels": []
    },
    {
        "match_id": 15010558,
        "kickoff": 1768491900,
        "fixture": "Shabab Al-Ahli Dubai vs Ajman",
        "league_id": 971,
        "league": "Pro League",
        "venue": "TBA",
        "tv_channels": []
    },
    {
        "match_id": 14194025,
        "kickoff": 1768413600,
        "fixture": "Dijon FCO vs Paris Saint-Germain",
        "league_id": 1139,
        "league": "Première Ligue, Féminine",
        "venue": "TBA",
        "tv_channels": []
    },
    {
        "match_id": 14194027,
        "kickoff": 1768413600,
        "fixture": "Le Havre AC vs FC Fleury 91",
        "league_id": 1139,
        "league": "Première Ligue, Féminine",
        "venue": "TBA",
        "tv_channels": []
    },
    {
        "match_id": 14194028,
        "kickoff": 1768413600,
        "fixture": "OL Lyonnes vs RC Lens",
        "league_id": 1139,
        "league": "Première Ligue, Féminine",
        "venue": "TBA",
        "tv_channels": []
    },
    {
        "match_id": 14194026,
        "kickoff": 1768413600,
        "fixture": "Olympique de Marseille vs Saint-Étienne",
        "league_id": 1139,
        "league": "Première Ligue, Féminine",
        "venue": "TBA",
        "tv_channels": [
            {
                "country": "France",
                "channels": [
                    "Canal+ Foot"
                ]
            }
        ]
    },
    {
        "match_id": 14194030,
        "kickoff": 1768413600,
        "fixture": "Strasbourg vs Montpellier HSC",
        "league_id": 1139,
        "league": "Première Ligue, Féminine",
        "venue": "TBA",
        "tv_channels": []
    },
    {
        "match_id": 14194035,
        "kickoff": 1768420800,
        "fixture": "Paris FC vs Nantes",
        "league_id": 1139,
        "league": "Première Ligue, Féminine",
        "venue": "TBA",
        "tv_channels": [
            {
                "country": "France",
                "channels": [
                    "Canal+ Foot"
                ]
            }
        ]
    },
    {
        "match_id": 14414566,
        "kickoff": 1768413600,
        "fixture": "Fútbol Club Barcelona vs Club Atlético de Madrid",
        "league_id": 1127,
        "league": "Liga F Moeve",
        "venue": "TBA",
        "tv_channels": []
    },
    {
        "match_id": 14856353,
        "kickoff": 1768390200,
        "fixture": "Iraq U23 vs Australia U23",
        "league_id": 2349,
        "league": "U23 AFC Asian Cup, Group D",
        "venue": "Prince Faisal bin Fahd Stadium",
        "tv_channels": []
    },
    {
        "match_id": 14856352,
        "kickoff": 1768390200,
        "fixture": "Thailand U23 vs China U23",
        "league_id": 2349,
        "league": "U23 AFC Asian Cup, Group D",
        "venue": "Al-Shabab Club Stadium",
        "tv_channels": []
    },
    {
        "match_id": 15196053,
        "kickoff": 1768406400,
        "fixture": "A'ali vs Al Khaldiya",
        "league_id": 846,
        "league": "Premier League",
        "venue": "TBA",
        "tv_channels": []
    },
    {
        "match_id": 15196051,
        "kickoff": 1768406400,
        "fixture": "Malkiya vs Hidd",
        "league_id": 846,
        "league": "Premier League",
        "venue": "TBA",
        "tv_channels": []
    },
    {
        "match_id": 15196054,
        "kickoff": 1768492800,
        "fixture": "Al Ahli vs Muharraq",
        "league_id": 846,
        "league": "Premier League",
        "venue": "TBA",
        "tv_channels": []
    },
    {
        "match_id": 15196055,
        "kickoff": 1768492800,
        "fixture": "Al Bahrain vs Sitra",
        "league_id": 846,
        "league": "Premier League",
        "venue": "TBA",
        "tv_channels": []
    },
    {
        "match_id": 15183816,
        "kickoff": 1768419000,
        "fixture": "FCV Dender vs Royale Union Saint-Gilloise",
        "league_id": 326,
        "league": "Beker van Belgie",
        "venue": "TBA",
        "tv_channels": []
    },
    {
        "match_id": 15183817,
        "kickoff": 1768505400,
        "fixture": "RSC Anderlecht vs KAA Gent",
        "league_id": 326,
        "league": "Beker van Belgie",
        "venue": "TBA",
        "tv_channels": []
    },
    {
        "match_id": 15138023,
        "kickoff": 1768420800,
        "fixture": "Volta Redonda Futebol Clube vs Boavista",
        "league_id": 92,
        "league": "Carioca Série A – Taça Guanabara",
        "venue": "TBA",
        "tv_channels": []
    },
    {
        "match_id": 15138021,
        "kickoff": 1768428000,
        "fixture": "Fluminense vs Madureira",
        "league_id": 92,
        "league": "Carioca Série A – Taça Guanabara",
        "venue": "TBA",
        "tv_channels": []
    },
    {
        "match_id": 15138025,
        "kickoff": 1768437000,
        "fixture": "Bangu Atlético Clube vs Flamengo",
        "league_id": 92,
        "league": "Carioca Série A – Taça Guanabara",
        "venue": "TBA",
        "tv_channels": []
    },
    {
        "match_id": 15138024,
        "kickoff": 1768507200,
        "fixture": "Sampaio Corrêa-RJ vs Nova Iguaçu",
        "league_id": 92,
        "league": "Carioca Série A – Taça Guanabara",
        "venue": "TBA",
        "tv_channels": []
    },
    {
        "match_id": 15138026,
        "kickoff": 1768514400,
        "fixture": "Portuguesa-RJ vs Botafogo",
        "league_id": 92,
        "league": "Carioca Série A – Taça Guanabara",
        "venue": "TBA",
        "tv_channels": []
    },
    {
        "match_id": 15138022,
        "kickoff": 1768523400,
        "fixture": "Vasco da Gama vs Maricá FC",
        "league_id": 92,
        "league": "Carioca Série A – Taça Guanabara",
        "venue": "TBA",
        "tv_channels": []
    },
    {
        "match_id": 15146333,
        "kickoff": 1768428000,
        "fixture": "Inter de Santa Maria vs São Luiz",
        "league_id": 377,
        "league": "Gaúcho",
        "venue": "TBA",
        "tv_channels": []
    },
    {
        "match_id": 15146329,
        "kickoff": 1768428000,
        "fixture": "Novo Hamburgo vs Juventude",
        "league_id": 377,
        "league": "Gaúcho",
        "venue": "TBA",
        "tv_channels": []
    },
    {
        "match_id": 15146328,
        "kickoff": 1768437000,
        "fixture": "Caxias vs EC Avenida",
        "league_id": 377,
        "league": "Gaúcho",
        "venue": "TBA",
        "tv_channels": []
    },
    {
        "match_id": 15146331,
        "kickoff": 1768437000,
        "fixture": "Grêmio vs EC São José",
        "league_id": 377,
        "league": "Gaúcho",
        "venue": "TBA",
        "tv_channels": []
    },
    {
        "match_id": 15146330,
        "kickoff": 1768514400,
        "fixture": "Monsoon vs Internacional",
        "league_id": 377,
        "league": "Gaúcho",
        "venue": "TBA",
        "tv_channels": []
    },
    {
        "match_id": 15146332,
        "kickoff": 1768514400,
        "fixture": "Ypiranga FC vs Guarany de Bagé",
        "league_id": 377,
        "league": "Gaúcho",
        "venue": "TBA",
        "tv_channels": []
    },
    {
        "match_id": 15188770,
        "kickoff": 1768413600,
        "fixture": "EC Democrata vs América Mineiro",
        "league_id": 379,
        "league": "Mineiro Módulo I ",
        "venue": "TBA",
        "tv_channels": []
    },
    {
        "match_id": 15188769,
        "kickoff": 1768426200,
        "fixture": "Betim Futebol vs Uberlândia EC",
        "league_id": 379,
        "league": "Mineiro Módulo I ",
        "venue": "TBA",
        "tv_channels": []
    },
    {
        "match_id": 15188765,
        "kickoff": 1768428000,
        "fixture": "Athletic Club vs União Recreativa dos Trabalhadores",
        "league_id": 379,
        "league": "Mineiro Módulo I ",
        "venue": "TBA",
        "tv_channels": []
    },
    {
        "match_id": 15188767,
        "kickoff": 1768429800,
        "fixture": "North Esporte Clube vs Atlético Mineiro",
        "league_id": 379,
        "league": "Mineiro Módulo I ",
        "venue": "TBA",
        "tv_channels": []
    },
    {
        "match_id": 15188768,
        "kickoff": 1768435200,
        "fixture": "Pouso Alegre FC vs Itabirito FC",
        "league_id": 379,
        "league": "Mineiro Módulo I ",
        "venue": "TBA",
        "tv_channels": []
    },
    {
        "match_id": 15188766,
        "kickoff": 1768437000,
        "fixture": "Tombense vs Cruzeiro",
        "league_id": 379,
        "league": "Mineiro Módulo I ",
        "venue": "TBA",
        "tv_channels": []
    },
    {
        "match_id": 15204424,
        "kickoff": 1768428000,
        "fixture": "Decisão Goiana vs Clube Náutico Capibaribe",
        "league_id": 380,
        "league": "Pernambucano, Serie A1",
        "venue": "TBA",
        "tv_channels": []
    },
    {
        "match_id": 15204437,
        "kickoff": 1768433400,
        "fixture": "Maguary vs Santa Cruz",
        "league_id": 380,
        "league": "Pernambucano, Serie A1",
        "venue": "TBA",
        "tv_channels": []
    },
    {
        "match_id": 15204429,
        "kickoff": 1768437000,
        "fixture": "Sport Recife vs Retrô",
        "league_id": 380,
        "league": "Pernambucano, Serie A1",
        "venue": "TBA",
        "tv_channels": []
    },
    {
        "match_id": 15298489,
        "kickoff": 1768523400,
        "fixture": "Junior Barranquilla vs Independiente Santa Fe",
        "league_id": 10756,
        "league": "Super Cup",
        "venue": "TBA",
        "tv_channels": []
    },
    {
        "match_id": 15188412,
        "kickoff": 1768438800,
        "fixture": "Sporting FC vs Herediano",
        "league_id": 11542,
        "league": "Primera División, Clausura",
        "venue": "TBA",
        "tv_channels": []
    },
    {
        "match_id": 15188391,
        "kickoff": 1768442400,
        "fixture": "CS Cartaginés vs Guadalupe FC",
        "league_id": 11542,
        "league": "Primera División, Clausura",
        "venue": "TBA",
        "tv_channels": []
    },
    {
        "match_id": 15188394,
        "kickoff": 1768528800,
        "fixture": "LD Alajuelense vs Municipal Liberia",
        "league_id": 11542,
        "league": "Primera División, Clausura",
        "venue": "TBA",
        "tv_channels": []
    },
    {
        "match_id": 15337493,
        "kickoff": 1768469400,
        "fixture": "MFK Chrudim vs FC Hradec Kralove B",
        "league_id": 1224,
        "league": "Winter League, Group B",
        "venue": "TBA",
        "tv_channels": []
    },
    {
        "match_id": 15337491,
        "kickoff": 1768555800,
        "fixture": "Slovan Liberec U21 vs Mladá Boleslav",
        "league_id": 1224,
        "league": "Winter League, Group B",
        "venue": "TBA",
        "tv_channels": []
    },
    {
        "match_id": 15254197,
        "kickoff": 1768392000,
        "fixture": "MFK Skalica vs FC Zlín",
        "league_id": 1224,
        "league": "Winter League, Group C",
        "venue": "TBA",
        "tv_channels": []
    },
    {
        "match_id": 15254199,
        "kickoff": 1768478400,
        "fixture": "1. FC Tatran Prešov vs OFK Dynamo Malženice",
        "league_id": 1224,
        "league": "Winter League, Group D",
        "venue": "TBA",
        "tv_channels": []
    },
    {
        "match_id": 15324736,
        "kickoff": 1768395600,
        "fixture": "APO Levadiakos vs AE Kifisia",
        "league_id": 375,
        "league": "Greece Cup, Playoffs",
        "venue": "TBA",
        "tv_channels": []
    },
    {
        "match_id": 15328516,
        "kickoff": 1768402800,
        "fixture": "AEK Athens vs OFI Crete",
        "league_id": 375,
        "league": "Greece Cup, Playoffs",
        "venue": "TBA",
        "tv_channels": []
    },
    {
        "match_id": 15324735,
        "kickoff": 1768408200,
        "fixture": "Olympiacos FC vs PAOK",
        "league_id": 375,
        "league": "Greece Cup, Playoffs",
        "venue": "TBA",
        "tv_channels": []
    },
    {
        "match_id": 15324737,
        "kickoff": 1768415400,
        "fixture": "Panathinaikos vs Aris Thessaloniki",
        "league_id": 375,
        "league": "Greece Cup, Playoffs",
        "venue": "TBA",
        "tv_channels": []
    },
    {
        "match_id": 15214968,
        "kickoff": 1768397400,
        "fixture": "Renate vs Latina",
        "league_id": 824,
        "league": "Coppa Italia Serie C, Knockout stage",
        "venue": "TBA",
        "tv_channels": []
    },
    {
        "match_id": 15214969,
        "kickoff": 1768410000,
        "fixture": "Ternana vs Potenza Calcio",
        "league_id": 824,
        "league": "Coppa Italia Serie C, Knockout stage",
        "venue": "TBA",
        "tv_channels": []
    },
    {
        "match_id": 14068605,
        "kickoff": 1768561200,
        "fixture": "Lazio U20 vs Sassuolo U20",
        "league_id": 2292,
        "league": "Primavera 1",
        "venue": "TBA",
        "tv_channels": []
    },
    {
        "match_id": 14271749,
        "kickoff": 1768392900,
        "fixture": "Johor Darul Ta'zim vs Kuching City",
        "league_id": 1000,
        "league": "Super League",
        "venue": "TBA",
        "tv_channels": []
    },
    {
        "match_id": 14271752,
        "kickoff": 1768392900,
        "fixture": "Kuala Lumpur City FC vs Penang",
        "league_id": 1000,
        "league": "Super League",
        "venue": "TBA",
        "tv_channels": []
    },
    {
        "match_id": 14271755,
        "kickoff": 1768395600,
        "fixture": "Melaka FC vs PDRM FC",
        "league_id": 1000,
        "league": "Super League",
        "venue": "TBA",
        "tv_channels": []
    },
    {
        "match_id": 14271754,
        "kickoff": 1768395600,
        "fixture": "Selangor Football Club vs Negeri Sembilan",
        "league_id": 1000,
        "league": "Super League",
        "venue": "TBA",
        "tv_channels": []
    },
    {
        "match_id": 14336297,
        "kickoff": 1768508100,
        "fixture": "Vizela vs Paços de Ferreira",
        "league_id": 239,
        "league": "Liga Portugal 2",
        "venue": "Estádio do FC Vizela",
        "tv_channels": []
    },
    {
        "match_id": 15273948,
        "kickoff": 1768388400,
        "fixture": "Portimonense U23 vs Marítimo U23",
        "league_id": 11341,
        "league": "U23 Championship, Relegation Round",
        "venue": "TBA",
        "tv_channels": []
    },
    {
        "match_id": 15273950,
        "kickoff": 1768388400,
        "fixture": "Rio Ave U23 vs SC Farense U23",
        "league_id": 11341,
        "league": "U23 Championship, Relegation Round",
        "venue": "TBA",
        "tv_channels": []
    },
    {
        "match_id": 15274993,
        "kickoff": 1768402800,
        "fixture": "UD Leiria U23 vs Estrela Amadora U23",
        "league_id": 11341,
        "league": "U23 Championship, Relegation Round",
        "venue": "TBA",
        "tv_channels": []
    },
    {
        "match_id": 15273949,
        "kickoff": 1768402800,
        "fixture": "Vizela U23 vs Gil Vicente U23",
        "league_id": 11341,
        "league": "U23 Championship, Relegation Round",
        "venue": "TBA",
        "tv_channels": []
    },
    {
        "match_id": 14195510,
        "kickoff": 1768563000,
        "fixture": "Geylang International vs Hougang United",
        "league_id": 634,
        "league": "Premier League",
        "venue": "Our Tampines Hub",
        "tv_channels": []
    },
    {
        "match_id": 14195523,
        "kickoff": 1768563000,
        "fixture": "Tampines Rovers vs Young Lions",
        "league_id": 634,
        "league": "Premier League",
        "venue": "Our Tampines Hub",
        "tv_channels": []
    },
    {
        "match_id": 15332921,
        "kickoff": 1768482000,
        "fixture": "AS Soliman vs JS Kairouanaise",
        "league_id": 984,
        "league": "Ligue 1",
        "venue": "TBA",
        "tv_channels": []
    },
    {
        "match_id": 15332919,
        "kickoff": 1768482000,
        "fixture": "Espérance Tunis vs Avenir Sportif De Gabes",
        "league_id": 984,
        "league": "Ligue 1",
        "venue": "TBA",
        "tv_channels": []
    },
    {
        "match_id": 15329122,
        "kickoff": 1768428000,
        "fixture": "Boca Juniors vs Millonarios",
        "league_id": 853,
        "league": "Club Friendly Games",
        "venue": "TBA",
        "tv_channels": []
    }
]
