{
  "matches": [
    {
      "team1": "Rajasthan Royals",
      "team2": "Lucknow Super Giants",
      "team1_logo": "https://i1.wp.com/api.sofascore1.com/api/v1/team/187842/image",
      "team2_logo": "https://i1.wp.com/api.sofascore1.com/api/v1/team/410010/image",
      "league_logo": "https://api.sofascore1.com/api/v1/unique-tournament/40604/image",
      "league": "Indian Premier League",
      "start": "2026-05-19T23:00:00+09:00",
      "league_id": 40604,
      "duration": 8,
      "details_url": "https://www.yosintv.net/match?yosintv=ipl"
    },
    {
      "team1": "Kolkata Knight Riders",
      "team2": "Mumbai Indians",
      "team1_logo": "https://i1.wp.com/api.sofascore1.com/api/v1/team/187775/image",
      "team2_logo": "https://i1.wp.com/api.sofascore1.com/api/v1/team/187780/image",
      "league_logo": "https://api.sofascore1.com/api/v1/unique-tournament/40604/image",
      "league": "Indian Premier League",
      "start": "2026-05-20T23:00:00+09:00",
      "league_id": 40604,
      "duration": 8,
      "details_url": "https://www.yosintv.net/match?yosintv=ipl"
    }
  ]
}
