{
  "matches": [
    {
      "team1": "Sassuolo",
      "team1_logo": "https://i1.wp.com/api.sofascore1.com/api/v1/team/2793/image",
      "team2": "Milan",
      "team2_logo": "https://i1.wp.com/api.sofascore1.com/api/v1/team/2692/image",
      "league": "Serie A",
      "start": "2026-05-03T22:00:00+09:00",
      "duration": 2.2,
      "details_url": "https://blog.cricfoot.net/?yosintv=milan"
    },
    {
      "team1": "Lille",
      "team1_logo": "https://i1.wp.com/api.sofascore1.com/api/v1/team/1643/image",
      "team2": "Le Havre",
      "team2_logo": "https://i1.wp.com/api.sofascore1.com/api/v1/team/1662/image",
      "league": "Ligue 1",
      "start": "2026-05-03T22:00:00+09:00",
      "duration": 2.2,
      "details_url": "https://blog.cricfoot.net/?yosintv=lille"
    },
    {
      "team1": "Manchester United",
      "team1_logo": "https://i1.wp.com/api.sofascore1.com/api/v1/team/35/image",
      "team2": "Liverpool FC",
      "team2_logo": "https://i1.wp.com/api.sofascore1.com/api/v1/team/44/image",
      "league": "Premier League",
      "start": "2026-05-03T23:30:00+09:00",
      "duration": 2.2,
      "details_url": "https://blog.cricfoot.net/?yosintv=manchesterunited"
    },
    {
      "team1": "Borussia M'gladbach",
      "team1_logo": "https://i1.wp.com/api.sofascore1.com/api/v1/team/2527/image",
      "team2": "Borussia Dortmund",
      "team2_logo": "https://i1.wp.com/api.sofascore1.com/api/v1/team/2673/image",
      "league": "Bundesliga",
      "start": "2026-05-04T00:30:00+09:00",
      "duration": 2.2,
      "details_url": "https://blog.cricfoot.net/?yosintv=borussiadortmund"
    },
    {
      "team1": "Juventus",
      "team1_logo": "https://i1.wp.com/api.sofascore1.com/api/v1/team/2687/image",
      "team2": "Hellas Verona",
      "team2_logo": "https://i1.wp.com/api.sofascore1.com/api/v1/team/2701/image",
      "league": "Serie A",
      "start": "2026-05-04T01:00:00+09:00",
      "duration": 2.2,
      "details_url": "https://blog.cricfoot.net/?yosintv=juventus"
    },
    {
      "team1": "Real Betis",
      "team1_logo": "https://i1.wp.com/api.sofascore1.com/api/v1/team/2816/image",
      "team2": "Real Oviedo",
      "team2_logo": "https://i1.wp.com/api.sofascore1.com/api/v1/team/2851/image",
      "league": "LaLiga",
      "start": "2026-05-04T01:30:00+09:00",
      "duration": 2.2,
      "details_url": "https://blog.cricfoot.net/?yosintv=realbetis"
    },
    {
      "team1": "Aston Villa",
      "team1_logo": "https://i1.wp.com/api.sofascore1.com/api/v1/team/40/image",
      "team2": "Tottenham Hotspur",
      "team2_logo": "https://i1.wp.com/api.sofascore1.com/api/v1/team/33/image",
      "league": "Premier League",
      "start": "2026-05-04T03:00:00+09:00",
      "duration": 2.2,
      "details_url": "https://blog.cricfoot.net/?yosintv=astonvilla"
    },
    {
      "team1": "Al-Qadsiah",
      "team1_logo": "https://i1.wp.com/api.sofascore1.com/api/v1/team/56027/image",
      "team2": "Al-Nassr",
      "team2_logo": "https://i1.wp.com/api.sofascore1.com/api/v1/team/23400/image",
      "league": "Saudi Pro League",
      "start": "2026-05-04T03:00:00+09:00",
      "duration": 2.2,
      "details_url": "https://blog.cricfoot.net/?yosintv=alnassr"
    },
    {
      "team1": "Inter",
      "team1_logo": "https://i1.wp.com/api.sofascore1.com/api/v1/team/2697/image",
      "team2": "Parma",
      "team2_logo": "https://i1.wp.com/api.sofascore1.com/api/v1/team/2690/image",
      "league": "Serie A",
      "start": "2026-05-04T03:45:00+09:00",
      "duration": 2.2,
      "details_url": "https://blog.cricfoot.net/?yosintv=inter"
    },
    {
      "team1": "Olympique Lyonnais",
      "team1_logo": "https://i1.wp.com/api.sofascore1.com/api/v1/team/1649/image",
      "team2": "Stade Rennais",
      "team2_logo": "https://i1.wp.com/api.sofascore1.com/api/v1/team/1658/image",
      "league": "Ligue 1",
      "start": "2026-05-04T03:45:00+09:00",
      "duration": 2.2,
      "details_url": "https://blog.cricfoot.net/?yosintv=olympiquelyonnais"
    },
    {
      "team1": "Espanyol",
      "team1_logo": "https://i1.wp.com/api.sofascore1.com/api/v1/team/2814/image",
      "team2": "Real Madrid",
      "team2_logo": "https://i1.wp.com/api.sofascore1.com/api/v1/team/2829/image",
      "league": "LaLiga",
      "start": "2026-05-04T04:00:00+09:00",
      "duration": 2.2,
      "details_url": "https://blog.cricfoot.net/?yosintv=espanyol"
    },
    {
      "team1": "Chelsea",
      "team1_logo": "https://i1.wp.com/api.sofascore1.com/api/v1/team/38/image",
      "team2": "Nottingham Forest",
      "team2_logo": "https://i1.wp.com/api.sofascore1.com/api/v1/team/14/image",
      "league": "Premier League",
      "start": "2026-05-04T23:00:00+09:00",
      "duration": 2.2,
      "details_url": "https://blog.cricfoot.net/?yosintv=chelsea"
    }
  ]
}
