{
  "matches": [
    {
      "team1": "Celta Vigo",
      "team1_logo": "https://i1.wp.com/api.sofascore1.com/api/v1/team/2821/image",
      "team2": "Levante UD",
      "team2_logo": "https://i1.wp.com/api.sofascore1.com/api/v1/team/2849/image",
      "league": "LaLiga",
      "start": "2026-05-13T02:00:00+09:00",
      "duration": 2.2,
      "details_url": "https://www.yosintv.net/match?yosintv=celtavigo"
    },
    {
      "team1": "Real Betis",
      "team1_logo": "https://i1.wp.com/api.sofascore1.com/api/v1/team/2816/image",
      "team2": "Elche",
      "team2_logo": "https://i1.wp.com/api.sofascore1.com/api/v1/team/2846/image",
      "league": "LaLiga",
      "start": "2026-05-13T03:00:00+09:00",
      "duration": 2.2,
      "details_url": "https://www.yosintv.net/match?yosintv=realbetis"
    },
    {
      "team1": "Al-Nassr",
      "team1_logo": "https://i1.wp.com/api.sofascore1.com/api/v1/team/23400/image",
      "team2": "Al-Hilal",
      "team2_logo": "https://i1.wp.com/api.sofascore1.com/api/v1/team/21895/image",
      "league": "Saudi Pro League",
      "start": "2026-05-13T03:00:00+09:00",
      "duration": 2.2,
      "details_url": "https://www.yosintv.net/match?yosintv=alnassr"
    },
    {
      "team1": "Osasuna",
      "team1_logo": "https://i1.wp.com/api.sofascore1.com/api/v1/team/2820/image",
      "team2": "Atlético Madrid",
      "team2_logo": "https://i1.wp.com/api.sofascore1.com/api/v1/team/2836/image",
      "league": "LaLiga",
      "start": "2026-05-13T04:30:00+09:00",
      "duration": 2.2,
      "details_url": "https://www.yosintv.net/match?yosintv=atleticomadrid"
    }
  ]
}
